MANIFEST.in
sale_mrp_view.xml
setup.py
./__init__.py
./__openerp__.py
./sale_mrp.py
i18n/ar.po
i18n/bg.po
i18n/bs.po
i18n/ca.po
i18n/cs.po
i18n/da.po
i18n/de.po
i18n/es.po
i18n/es_CL.po
i18n/es_CR.po
i18n/es_MX.po
i18n/es_VE.po
i18n/et.po
i18n/fi.po
i18n/fr.po
i18n/gl.po
i18n/hr.po
i18n/hu.po
i18n/it.po
i18n/ja.po
i18n/lt.po
i18n/mk.po
i18n/mn.po
i18n/nb.po
i18n/nl.po
i18n/nl_BE.po
i18n/pl.po
i18n/pt.po
i18n/pt_BR.po
i18n/ro.po
i18n/ru.po
i18n/sale_mrp.pot
i18n/sl.po
i18n/sr@latin.po
i18n/sv.po
i18n/th.po
i18n/tr.po
i18n/zh_CN.po
i18n/zh_TW.po
images/SO_to_MO.jpeg
openerp_sale_mrp.egg-info/PKG-INFO
openerp_sale_mrp.egg-info/SOURCES.txt
openerp_sale_mrp.egg-info/dependency_links.txt
openerp_sale_mrp.egg-info/requires.txt
openerp_sale_mrp.egg-info/top_level.txt
security/ir.model.access.csv
test/sale_mrp.yml